[
    {
        "key": "dbln",
        "value": "%7B%2261566311011541%22%3A%22PDhePVe9%22%7D",
        "domain": "facebook.com",
        "path": "/login/device-based/",
        "hostOnly": false,
        "creation": "2024-12-13T09:52:48.448Z",
        "lastAccessed": "2024-12-13T09:52:48.448Z"
    },
    {
        "key": "sb",
        "value": "XBgcZ4fYdD7HXM9R-uSBTyFW",
        "domain": "facebook.com",
        "path": "/",
        "hostOnly": false,
        "creation": "2024-12-13T09:52:48.448Z",
        "lastAccessed": "2024-12-13T09:52:48.448Z"
    },
    {
        "key": "dpr",
        "value": "2.1988937854766846",
        "domain": "facebook.com",
        "path": "/",
        "hostOnly": false,
        "creation": "2024-12-13T09:52:48.448Z",
        "lastAccessed": "2024-12-13T09:52:48.448Z"
    },
    {
        "key": "ps_l",
        "value": "1",
        "domain": "facebook.com",
        "path": "/",
        "hostOnly": false,
        "creation": "2024-12-13T09:52:48.448Z",
        "lastAccessed": "2024-12-13T09:52:48.448Z"
    },
    {
        "key": "ps_n",
        "value": "1",
        "domain": "facebook.com",
        "path": "/",
        "hostOnly": false,
        "creation": "2024-12-13T09:52:48.448Z",
        "lastAccessed": "2024-12-13T09:52:48.448Z"
    },
    {
        "key": "wd",
        "value": "891x1654",
        "domain": "facebook.com",
        "path": "/",
        "hostOnly": false,
        "creation": "2024-12-13T09:52:48.448Z",
        "lastAccessed": "2024-12-13T09:52:48.448Z"
    },
    {
        "key": "c_user",
        "value": "61566311011541",
        "domain": "facebook.com",
        "path": "/",
        "hostOnly": false,
        "creation": "2024-12-13T09:52:48.448Z",
        "lastAccessed": "2024-12-13T09:52:48.448Z"
    },
    {
        "key": "datr",
        "value": "5gNcZxFrFVwrjTZudsxkgrsc",
        "domain": "facebook.com",
        "path": "/",
        "hostOnly": false,
        "creation": "2024-12-13T09:52:48.448Z",
        "lastAccessed": "2024-12-13T09:52:48.448Z"
    },
    {
        "key": "xs",
        "value": "18%3A7lR-J9pt8V4wbA%3A2%3A1734083558%3A-1%3A13443",
        "domain": "facebook.com",
        "path": "/",
        "hostOnly": false,
        "creation": "2024-12-13T09:52:48.448Z",
        "lastAccessed": "2024-12-13T09:52:48.448Z"
    },
    {
        "key": "fr",
        "value": "199azCP2LZtH7jrnZ.AWWZ7B9CnHqpYKCfnZpc6I08ZPw.BnWubJ..AAA.0.0.BnXAPp.AWV6j-sCqJ4",
        "domain": "facebook.com",
        "path": "/",
        "hostOnly": false,
        "creation": "2024-12-13T09:52:48.448Z",
        "lastAccessed": "2024-12-13T09:52:48.448Z"
    }
]
